[
  {
    "_key": "1974368a-4c0c-4d58-856e-39eaf907368d",
    "_id": "documents/1974368a-4c0c-4d58-856e-39eaf907368d",
    "created_at": "2026-01-25T10:57:46.017702Z",
    "updated_at": "2026-01-25T10:57:49.574982Z",
    "name": "Overview",
    "description": "overview",
    "data": "[{\"id\":\"69390829-b279-445e-b8a0-1bc59d9367dc\",\"type\":\"heading\",\"props\":{\"backgroundColor\":\"default\",\"textColor\":\"default\",\"textAlignment\":\"left\",\"level\":1,\"isToggleable\":false},\"content\":[{\"type\":\"text\",\"text\":\"_clear_caches\",\"styles\":{\"code\":true}},{\"type\":\"text\",\"text\":\" Function Documentation\",\"styles\":{}}],\"children\":[]},{\"id\":\"e1a26a56-08dd-43a3-a9b5-a05c8e1acc72\",\"type\":\"heading\",\"props\":{\"backgroundColor\":\"default\",\"textColor\":\"default\",\"textAlignment\":\"left\",\"level\":2,\"isToggleable\":false},\"content\":[{\"type\":\"text\",\"text\":\"Overview\",\"styles\":{}}],\"children\":[]},{\"id\":\"36e37915-bb8f-4789-876e-868a34236b00\",\"type\":\"paragraph\",\"props\":{\"backgroundColor\":\"default\",\"textColor\":\"default\",\"textAlignment\":\"left\"},\"content\":[{\"type\":\"text\",\"text\":\"_clear_caches\",\"styles\":{\"code\":true}},{\"type\":\"text\",\"text\":\" resets Python\u2019s import-related caches to ensure that changes to the import system are applied immediately and consistently.\",\"styles\":{}}],\"children\":[]},{\"id\":\"13f28d69-6389-489d-86ed-ad5add410c7c\",\"type\":\"heading\",\"props\":{\"backgroundColor\":\"default\",\"textColor\":\"default\",\"textAlignment\":\"left\",\"level\":3,\"isToggleable\":false},\"content\":[{\"type\":\"text\",\"text\":\"Purpose\",\"styles\":{}}],\"children\":[]},{\"id\":\"b313d19d-1544-451b-b567-1edbe161523e\",\"type\":\"paragraph\",\"props\":{\"backgroundColor\":\"default\",\"textColor\":\"default\",\"textAlignment\":\"left\"},\"content\":[{\"type\":\"text\",\"text\":\"Python caches import lookups for performance. When custom import hooks or path changes are introduced, those caches must be cleared so the new configuration is honored. This function performs that reset.\",\"styles\":{}}],\"children\":[]},{\"id\":\"8a4f12e6-4bbe-41fe-bfa7-8511e923435f\",\"type\":\"divider\",\"props\":{},\"children\":[]},{\"id\":\"1c26e212-c229-4502-96f1-b96b31081664\",\"type\":\"heading\",\"props\":{\"backgroundColor\":\"default\",\"textColor\":\"default\",\"textAlignment\":\"left\",\"level\":2,\"isToggleable\":false},\"content\":[{\"type\":\"text\",\"text\":\"What the Function Does\",\"styles\":{}}],\"children\":[]},{\"id\":\"e8f37273-fe56-43be-a413-fd2ba9b66994\",\"type\":\"paragraph\",\"props\":{\"backgroundColor\":\"default\",\"textColor\":\"default\",\"textAlignment\":\"left\"},\"content\":[{\"type\":\"text\",\"text\":\"At a high level, \",\"styles\":{}},{\"type\":\"text\",\"text\":\"_clear_caches\",\"styles\":{\"code\":true}},{\"type\":\"text\",\"text\":\":\",\"styles\":{}}],\"children\":[]},{\"id\":\"e0a33bad-094b-40db-a29b-5c51d61d6ca9\",\"type\":\"bulletListItem\",\"props\":{\"backgroundColor\":\"default\",\"textColor\":\"default\",\"textAlignment\":\"left\"},\"content\":[{\"type\":\"text\",\"text\":\"Invalidates internal caches used by \",\"styles\":{}},{\"type\":\"text\",\"text\":\"importlib\",\"styles\":{\"code\":true}}],\"children\":[]},{\"id\":\"fdc73129-6661-4510-8e00-4ae152ff8e00\",\"type\":\"bulletListItem\",\"props\":{\"backgroundColor\":\"default\",\"textColor\":\"default\",\"textAlignment\":\"left\"},\"content\":[{\"type\":\"text\",\"text\":\"Clears the cached importers stored in \",\"styles\":{}},{\"type\":\"text\",\"text\":\"sys.path_importer_cache\",\"styles\":{\"code\":true}}],\"children\":[]},{\"id\":\"26d01cda-dd8c-4756-8524-23a06e282f0d\",\"type\":\"paragraph\",\"props\":{\"backgroundColor\":\"default\",\"textColor\":\"default\",\"textAlignment\":\"left\"},\"content\":[{\"type\":\"text\",\"text\":\"It does not modify the dependency graph or perform import analysis itself.\",\"styles\":{}}],\"children\":[]},{\"id\":\"481ddcc4-6e0d-47c0-852d-5b548c6c659c\",\"type\":\"divider\",\"props\":{},\"children\":[]},{\"id\":\"de671ffd-ba51-4202-89c4-687087416123\",\"type\":\"heading\",\"props\":{\"backgroundColor\":\"default\",\"textColor\":\"default\",\"textAlignment\":\"left\",\"level\":2,\"isToggleable\":false},\"content\":[{\"type\":\"text\",\"text\":\"Key Responsibilities\",\"styles\":{}}],\"children\":[]},{\"id\":\"d5c50df7-40ff-40d9-b474-6b47cbde3ce0\",\"type\":\"bulletListItem\",\"props\":{\"backgroundColor\":\"default\",\"textColor\":\"default\",\"textAlignment\":\"left\"},\"content\":[{\"type\":\"text\",\"text\":\"Synchronization:\",\"styles\":{\"bold\":true}},{\"type\":\"text\",\"text\":\" Ensures Python recognizes new import hooks and paths\",\"styles\":{}}],\"children\":[]},{\"id\":\"846aa7a7-7ca7-4972-9042-5f7efa78164a\",\"type\":\"bulletListItem\",\"props\":{\"backgroundColor\":\"default\",\"textColor\":\"default\",\"textAlignment\":\"left\"},\"content\":[{\"type\":\"text\",\"text\":\"Accuracy:\",\"styles\":{\"bold\":true}},{\"type\":\"text\",\"text\":\" Prevents stale cache entries from bypassing custom loaders\",\"styles\":{}}],\"children\":[]},{\"id\":\"4ed19c1e-c176-45b9-8fe0-ee6427ce1090\",\"type\":\"bulletListItem\",\"props\":{\"backgroundColor\":\"default\",\"textColor\":\"default\",\"textAlignment\":\"left\"},\"content\":[{\"type\":\"text\",\"text\":\"Isolation:\",\"styles\":{\"bold\":true}},{\"type\":\"text\",\"text\":\" Keeps cache handling centralized and explicit\",\"styles\":{}}],\"children\":[]},{\"id\":\"f720ba06-84a6-4a44-9f9d-954f9e0d5f30\",\"type\":\"divider\",\"props\":{},\"children\":[]},{\"id\":\"765d42c4-1bcd-4ced-9271-a1ad8a6425a2\",\"type\":\"heading\",\"props\":{\"backgroundColor\":\"default\",\"textColor\":\"default\",\"textAlignment\":\"left\",\"level\":2,\"isToggleable\":false},\"content\":[{\"type\":\"text\",\"text\":\"Behavior Summary\",\"styles\":{}}],\"children\":[]},{\"id\":\"3aa845af-0137-43e9-92a4-3eb65d1432a2\",\"type\":\"codeBlock\",\"props\":{\"language\":\"javascript\"},\"content\":[{\"type\":\"text\",\"text\":\"Process:\\n  1. Invalidate importlib caches\\n  2. Clear sys.path_importer_cache\\n\\nResult:\\n  Python re-evaluates import hooks and paths on next import\",\"styles\":{}}],\"children\":[]},{\"id\":\"3610563e-3d60-4cef-bda5-ce0dc4151ead\",\"type\":\"divider\",\"props\":{},\"children\":[]},{\"id\":\"22320e5a-d642-4fb1-a3a7-39d87da67ad7\",\"type\":\"heading\",\"props\":{\"backgroundColor\":\"default\",\"textColor\":\"default\",\"textAlignment\":\"left\",\"level\":2,\"isToggleable\":false},\"content\":[{\"type\":\"text\",\"text\":\"When It Is Used\",\"styles\":{}}],\"children\":[]},{\"id\":\"10cbcaa0-e034-4887-8d06-b4ed11eb8e2c\",\"type\":\"bulletListItem\",\"props\":{\"backgroundColor\":\"default\",\"textColor\":\"default\",\"textAlignment\":\"left\"},\"content\":[{\"type\":\"text\",\"text\":\"Immediately after \",\"styles\":{}},{\"type\":\"text\",\"text\":\"installing import hooks\",\"styles\":{\"bold\":true}}],\"children\":[]},{\"id\":\"66d5bdc9-2ba5-4a86-bbe2-436b0cc74516\",\"type\":\"bulletListItem\",\"props\":{\"backgroundColor\":\"default\",\"textColor\":\"default\",\"textAlignment\":\"left\"},\"content\":[{\"type\":\"text\",\"text\":\"After \",\"styles\":{}},{\"type\":\"text\",\"text\":\"removing import hooks\",\"styles\":{\"bold\":true}}],\"children\":[]},{\"id\":\"45853395-0b5c-4897-a13c-a4d8edbc3530\",\"type\":\"bulletListItem\",\"props\":{\"backgroundColor\":\"default\",\"textColor\":\"default\",\"textAlignment\":\"left\"},\"content\":[{\"type\":\"text\",\"text\":\"Whenever the import system configuration changes\",\"styles\":{}}],\"children\":[]},{\"id\":\"2bd552ba-50f9-42a3-93c3-4c514e53afae\",\"type\":\"paragraph\",\"props\":{\"backgroundColor\":\"default\",\"textColor\":\"default\",\"textAlignment\":\"left\"},\"content\":[{\"type\":\"text\",\"text\":\"It is not part of the main import analysis loop and is called only during setup or cleanup.\",\"styles\":{}}],\"children\":[]},{\"id\":\"142b8a6f-dc46-43ed-8392-5d1de11591de\",\"type\":\"divider\",\"props\":{},\"children\":[]},{\"id\":\"8e04ecd8-d9e1-4d35-a614-5dbc1a2fafe4\",\"type\":\"heading\",\"props\":{\"backgroundColor\":\"default\",\"textColor\":\"default\",\"textAlignment\":\"left\",\"level\":2,\"isToggleable\":false},\"content\":[{\"type\":\"text\",\"text\":\"How It Fits in the System\",\"styles\":{}}],\"children\":[]},{\"id\":\"5e1c13d7-1ff2-4754-8136-53c80ffd23a8\",\"type\":\"bulletListItem\",\"props\":{\"backgroundColor\":\"default\",\"textColor\":\"default\",\"textAlignment\":\"left\"},\"content\":[{\"type\":\"text\",\"text\":\"Part of:\",\"styles\":{\"bold\":true}},{\"type\":\"text\",\"text\":\" Import System Control group\",\"styles\":{}}],\"children\":[]},{\"id\":\"17ca535f-df6c-4099-ac41-56a672815710\",\"type\":\"bulletListItem\",\"props\":{\"backgroundColor\":\"default\",\"textColor\":\"default\",\"textAlignment\":\"left\"},\"content\":[{\"type\":\"text\",\"text\":\"Called by:\",\"styles\":{\"bold\":true}},{\"type\":\"text\",\"text\":\" \",\"styles\":{}},{\"type\":\"text\",\"text\":\"install_hooks()\",\"styles\":{\"code\":true}},{\"type\":\"text\",\"text\":\", \",\"styles\":{}},{\"type\":\"text\",\"text\":\"remove_hooks()\",\"styles\":{\"code\":true}}],\"children\":[]},{\"id\":\"c2db032e-f685-462e-b13c-986123c08376\",\"type\":\"bulletListItem\",\"props\":{\"backgroundColor\":\"default\",\"textColor\":\"default\",\"textAlignment\":\"left\"},\"content\":[{\"type\":\"text\",\"text\":\"Supports:\",\"styles\":{\"bold\":true}},{\"type\":\"text\",\"text\":\" Reliable activation and deactivation of \",\"styles\":{}},{\"type\":\"text\",\"text\":\"CustomLoader\",\"styles\":{\"code\":true}}],\"children\":[]},{\"id\":\"733336f4-c135-41ec-8101-4f79f1325fd5\",\"type\":\"divider\",\"props\":{},\"children\":[]},{\"id\":\"6bace2ff-a247-4a60-ae9e-ed07f2d4f7d9\",\"type\":\"heading\",\"props\":{\"backgroundColor\":\"default\",\"textColor\":\"default\",\"textAlignment\":\"left\",\"level\":2,\"isToggleable\":false},\"content\":[{\"type\":\"text\",\"text\":\"Design Philosophy\",\"styles\":{}}],\"children\":[]},{\"id\":\"72ba469c-e85e-40d8-8133-63e2d7631c51\",\"type\":\"bulletListItem\",\"props\":{\"backgroundColor\":\"default\",\"textColor\":\"default\",\"textAlignment\":\"left\"},\"content\":[{\"type\":\"text\",\"text\":\"Minimal:\",\"styles\":{\"bold\":true}},{\"type\":\"text\",\"text\":\" Performs only cache invalidation\",\"styles\":{}}],\"children\":[]},{\"id\":\"5c284f24-7b2e-420f-85fd-86296d7d5bd5\",\"type\":\"bulletListItem\",\"props\":{\"backgroundColor\":\"default\",\"textColor\":\"default\",\"textAlignment\":\"left\"},\"content\":[{\"type\":\"text\",\"text\":\"Targeted:\",\"styles\":{\"bold\":true}},{\"type\":\"text\",\"text\":\" Touches only import-related caches\",\"styles\":{}}],\"children\":[]},{\"id\":\"7af45c6b-8ae3-4d4c-b8fe-f09011e4bacb\",\"type\":\"bulletListItem\",\"props\":{\"backgroundColor\":\"default\",\"textColor\":\"default\",\"textAlignment\":\"left\"},\"content\":[{\"type\":\"text\",\"text\":\"Safe:\",\"styles\":{\"bold\":true}},{\"type\":\"text\",\"text\":\" Uses standard Python mechanisms\",\"styles\":{}}],\"children\":[]},{\"id\":\"c0dcc1af-97e3-44e7-95ba-c8b6054e7cc0\",\"type\":\"divider\",\"props\":{},\"children\":[]},{\"id\":\"b33ce130-0af7-42c3-93e8-2174be1ec387\",\"type\":\"heading\",\"props\":{\"backgroundColor\":\"default\",\"textColor\":\"default\",\"textAlignment\":\"left\",\"level\":2,\"isToggleable\":false},\"content\":[{\"type\":\"text\",\"text\":\"Summary\",\"styles\":{}}],\"children\":[]},{\"id\":\"4389d5ff-8df2-4333-9917-5c393610fb61\",\"type\":\"table\",\"props\":{\"textColor\":\"default\"},\"content\":{\"type\":\"tableContent\",\"columnWidths\":[null,null],\"headerRows\":1,\"rows\":[{\"cells\":[{\"type\":\"tableCell\",\"content\":[{\"type\":\"text\",\"text\":\"Aspect\",\"styles\":{}}],\"props\":{\"colspan\":1,\"rowspan\":1,\"backgroundColor\":\"default\",\"textColor\":\"default\",\"textAlignment\":\"left\"}},{\"type\":\"tableCell\",\"content\":[{\"type\":\"text\",\"text\":\"Details\",\"styles\":{}}],\"props\":{\"colspan\":1,\"rowspan\":1,\"backgroundColor\":\"default\",\"textColor\":\"default\",\"textAlignment\":\"left\"}}]},{\"cells\":[{\"type\":\"tableCell\",\"content\":[{\"type\":\"text\",\"text\":\"Role\",\"styles\":{\"bold\":true}}],\"props\":{\"colspan\":1,\"rowspan\":1,\"backgroundColor\":\"default\",\"textColor\":\"default\",\"textAlignment\":\"left\"}},{\"type\":\"tableCell\",\"content\":[{\"type\":\"text\",\"text\":\"Synchronize Python import system state\",\"styles\":{}}],\"props\":{\"colspan\":1,\"rowspan\":1,\"backgroundColor\":\"default\",\"textColor\":\"default\",\"textAlignment\":\"left\"}}]},{\"cells\":[{\"type\":\"tableCell\",\"content\":[{\"type\":\"text\",\"text\":\"Group\",\"styles\":{\"bold\":true}}],\"props\":{\"colspan\":1,\"rowspan\":1,\"backgroundColor\":\"default\",\"textColor\":\"default\",\"textAlignment\":\"left\"}},{\"type\":\"tableCell\",\"content\":[{\"type\":\"text\",\"text\":\"Import System Control\",\"styles\":{}}],\"props\":{\"colspan\":1,\"rowspan\":1,\"backgroundColor\":\"default\",\"textColor\":\"default\",\"textAlignment\":\"left\"}}]},{\"cells\":[{\"type\":\"tableCell\",\"content\":[{\"type\":\"text\",\"text\":\"Impact\",\"styles\":{\"bold\":true}}],\"props\":{\"colspan\":1,\"rowspan\":1,\"backgroundColor\":\"default\",\"textColor\":\"default\",\"textAlignment\":\"left\"}},{\"type\":\"tableCell\",\"content\":[{\"type\":\"text\",\"text\":\"No graph changes, system-level effect\",\"styles\":{}}],\"props\":{\"colspan\":1,\"rowspan\":1,\"backgroundColor\":\"default\",\"textColor\":\"default\",\"textAlignment\":\"left\"}}]},{\"cells\":[{\"type\":\"tableCell\",\"content\":[{\"type\":\"text\",\"text\":\"Frequency\",\"styles\":{\"bold\":true}}],\"props\":{\"colspan\":1,\"rowspan\":1,\"backgroundColor\":\"default\",\"textColor\":\"default\",\"textAlignment\":\"left\"}},{\"type\":\"tableCell\",\"content\":[{\"type\":\"text\",\"text\":\"Setup and cleanup only\",\"styles\":{}}],\"props\":{\"colspan\":1,\"rowspan\":1,\"backgroundColor\":\"default\",\"textColor\":\"default\",\"textAlignment\":\"left\"}}]},{\"cells\":[{\"type\":\"tableCell\",\"content\":[{\"type\":\"text\",\"text\":\"Side Effects\",\"styles\":{\"bold\":true}}],\"props\":{\"colspan\":1,\"rowspan\":1,\"backgroundColor\":\"default\",\"textColor\":\"default\",\"textAlignment\":\"left\"}},{\"type\":\"tableCell\",\"content\":[{\"type\":\"text\",\"text\":\"Forces Python to re-evaluate imports\",\"styles\":{}}],\"props\":{\"colspan\":1,\"rowspan\":1,\"backgroundColor\":\"default\",\"textColor\":\"default\",\"textAlignment\":\"left\"}}]}]},\"children\":[]},{\"id\":\"974bf5f6-6b7d-427b-ac98-2cda4418e060\",\"type\":\"divider\",\"props\":{},\"children\":[]},{\"id\":\"a0d5f024-baf5-471b-a536-bb0b5fbf4442\",\"type\":\"heading\",\"props\":{\"backgroundColor\":\"default\",\"textColor\":\"default\",\"textAlignment\":\"left\",\"level\":2,\"isToggleable\":false},\"content\":[{\"type\":\"text\",\"text\":\"Next Steps\",\"styles\":{}}],\"children\":[]},{\"id\":\"5e7fcdd9-7f6f-4514-9324-d8fae50db8de\",\"type\":\"bulletListItem\",\"props\":{\"backgroundColor\":\"default\",\"textColor\":\"default\",\"textAlignment\":\"left\"},\"content\":[{\"type\":\"text\",\"text\":\"Review \",\"styles\":{}},{\"type\":\"text\",\"text\":\"install_hooks\",\"styles\":{\"code\":true}},{\"type\":\"text\",\"text\":\" to see when caches are cleared\",\"styles\":{}}],\"children\":[]},{\"id\":\"8f980394-043a-45a3-b9f4-3872f6f06bfc\",\"type\":\"bulletListItem\",\"props\":{\"backgroundColor\":\"default\",\"textColor\":\"default\",\"textAlignment\":\"left\"},\"content\":[{\"type\":\"text\",\"text\":\"See \",\"styles\":{}},{\"type\":\"text\",\"text\":\"remove_hooks\",\"styles\":{\"code\":true}},{\"type\":\"text\",\"text\":\" for system restoration\",\"styles\":{}}],\"children\":[]},{\"id\":\"b12bb771-33be-4b21-ab65-8e72610661fd\",\"type\":\"bulletListItem\",\"props\":{\"backgroundColor\":\"default\",\"textColor\":\"default\",\"textAlignment\":\"left\"},\"content\":[{\"type\":\"text\",\"text\":\"Explore \",\"styles\":{}},{\"type\":\"text\",\"text\":\"CustomLoader\",\"styles\":{\"bold\":true}},{\"type\":\"text\",\"text\":\" to understand how imports are intercepted\",\"styles\":{}}],\"children\":[]},{\"id\":\"23ad6e56-d9fe-4a1f-9142-f60f35bb0ff6\",\"type\":\"paragraph\",\"props\":{\"backgroundColor\":\"default\",\"textColor\":\"default\",\"textAlignment\":\"left\"},\"content\":[],\"children\":[]}]"
  }
]